{
  "color-primary-100": "#DDF6F6",
  "color-primary-200": "#BDEBEE",
  "color-primary-300": "#8DC5CD",
  "color-primary-400": "#5F8F9B",
  "color-primary-500": "#2B4D59",
  "color-primary-600": "#1F3D4C",
  "color-primary-700": "#152F40",
  "color-primary-800": "#0D2133",
  "color-primary-900": "#08182A",
  "color-primary-transparent-100": "rgba(43, 77, 89, 0.08)",
  "color-primary-transparent-200": "rgba(43, 77, 89, 0.16)",
  "color-primary-transparent-300": "rgba(43, 77, 89, 0.24)",
  "color-primary-transparent-400": "rgba(43, 77, 89, 0.32)",
  "color-primary-transparent-500": "rgba(43, 77, 89, 0.4)",
  "color-primary-transparent-600": "rgba(43, 77, 89, 0.48)",
  "color-success-100": "#DAF9EA",
  "color-success-200": "#B7F4DC",
  "color-success-300": "#8BE0C7",
  "color-success-400": "#66C1AE",
  "color-success-500": "#39998e",
  "color-success-600": "#298381",
  "color-success-700": "#1C686E",
  "color-success-800": "#124D58",
  "color-success-900": "#0A3949",
  "color-success-transparent-100": "rgba(57, 153, 142, 0.08)",
  "color-success-transparent-200": "rgba(57, 153, 142, 0.16)",
  "color-success-transparent-300": "rgba(57, 153, 142, 0.24)",
  "color-success-transparent-400": "rgba(57, 153, 142, 0.32)",
  "color-success-transparent-500": "rgba(57, 153, 142, 0.4)",
  "color-success-transparent-600": "rgba(57, 153, 142, 0.48)",
  "color-info-100": "#FFFAE4",
  "color-info-200": "#FFF5CA",
  "color-info-300": "#FFEEB0",
  "color-info-400": "#FFE79C",
  "color-info-500": "#ffdc7c",
  "color-info-600": "#DBB55A",
  "color-info-700": "#B7903E",
  "color-info-800": "#936D27",
  "color-info-900": "#7A5517",
  "color-info-transparent-100": "rgba(255, 220, 124, 0.08)",
  "color-info-transparent-200": "rgba(255, 220, 124, 0.16)",
  "color-info-transparent-300": "rgba(255, 220, 124, 0.24)",
  "color-info-transparent-400": "rgba(255, 220, 124, 0.32)",
  "color-info-transparent-500": "rgba(255, 220, 124, 0.4)",
  "color-info-transparent-600": "rgba(255, 220, 124, 0.48)",
  "color-warning-100": "#FFF4E0",
  "color-warning-200": "#FFE7C2",
  "color-warning-300": "#FFD6A3",
  "color-warning-400": "#FFC58D",
  "color-warning-500": "#ffaa67",
  "color-warning-600": "#DB824B",
  "color-warning-700": "#B75F33",
  "color-warning-800": "#934020",
  "color-warning-900": "#7A2A13",
  "color-warning-transparent-100": "rgba(255, 170, 103, 0.08)",
  "color-warning-transparent-200": "rgba(255, 170, 103, 0.16)",
  "color-warning-transparent-300": "rgba(255, 170, 103, 0.24)",
  "color-warning-transparent-400": "rgba(255, 170, 103, 0.32)",
  "color-warning-transparent-500": "rgba(255, 170, 103, 0.4)",
  "color-warning-transparent-600": "rgba(255, 170, 103, 0.48)",
  "color-danger-100": "#FDE2E5",
  "color-danger-200": "#FBC6D2",
  "color-danger-300": "#F3A6BF",
  "color-danger-400": "#E88CB3",
  "color-danger-500": "#da67a3",
  "color-danger-600": "#BB4B91",
  "color-danger-700": "#9C337F",
  "color-danger-800": "#7E206D",
  "color-danger-900": "#681361",
  "color-danger-transparent-100": "rgba(218, 103, 163, 0.08)",
  "color-danger-transparent-200": "rgba(218, 103, 163, 0.16)",
  "color-danger-transparent-300": "rgba(218, 103, 163, 0.24)",
  "color-danger-transparent-400": "rgba(218, 103, 163, 0.32)",
  "color-danger-transparent-500": "rgba(218, 103, 163, 0.4)",
  "color-danger-transparent-600": "rgba(218, 103, 163, 0.48)"
}
